kb4/__init__.py
kb4/exceptions.py
kb4/kb4.py
kb4.py-0.1.2.dist-info/LICENSE.md
kb4.py-0.1.2.dist-info/METADATA
kb4.py-0.1.2.dist-info/WHEEL
kb4.py-0.1.2.dist-info/top_level.txt
kb4.py-0.1.2.dist-info/RECORD
