Metadata-Version: 2.1
Name: kb4.py
Version: 0.1.2
Summary: A simple Python wrapper for the KnowBe4 API
Home-page: https://github.com/elderlydoofus/knowbe4.py
Author: Josh Thomas
Author-email: josh@joshuadavidthomas.com
License: LICENSE.md
Keywords: knowbe4,kb4.py
Platform: UNKNOWN
Classifier: Development Status :: 3 - Alpha
Classifier: License :: OSI Approved :: MIT License
Classifier: Operating System :: OS Independent
Classifier: Programming Language :: Python
Classifier: Programming Language :: Python :: 3
Classifier: Programming Language :: Python :: 3.6
Requires-Dist: requests (>=2.21.0)
